README.md
setup.py
import_profile/__init__.py
import_profile/__main__.py
import_profile/main.py
import_profile/probe.py
import_profile/version.py
import_profile.egg-info/PKG-INFO
import_profile.egg-info/SOURCES.txt
import_profile.egg-info/dependency_links.txt
import_profile.egg-info/requires.txt
import_profile.egg-info/top_level.txt