Metadata-Version: 2.1
Name: import-profile
Version: 0.1.1
Summary: Profile your imports' CPU and RAM usage
Home-page: https://hydra.ecd.space/eduard/import_profile/
Author: Eduard Christian Dumitrescu
Author-email: eduard.c.dumitrescu@gmail.com
License: LGPLv3
Platform: UNKNOWN
Classifier: Programming Language :: Python :: 3 :: Only
